odoo/addons/uom_unece/README.rst
odoo/addons/uom_unece/__init__.py
odoo/addons/uom_unece/__manifest__.py
odoo/addons/uom_unece/data/unece.xml
odoo/addons/uom_unece/i18n/de.po
odoo/addons/uom_unece/i18n/es.po
odoo/addons/uom_unece/i18n/fr.po
odoo/addons/uom_unece/i18n/hr.po
odoo/addons/uom_unece/i18n/it.po
odoo/addons/uom_unece/i18n/uom_unece.pot
odoo/addons/uom_unece/models/__init__.py
odoo/addons/uom_unece/models/uom_uom.py
odoo/addons/uom_unece/readme/CONFIGURE.md
odoo/addons/uom_unece/readme/CONTRIBUTORS.md
odoo/addons/uom_unece/readme/CREDITS.md
odoo/addons/uom_unece/readme/DESCRIPTION.md
odoo/addons/uom_unece/static/description/icon.png
odoo/addons/uom_unece/static/description/index.html
odoo/addons/uom_unece/views/uom_uom.xml
odoo_addon_uom_unece-19.0.1.0.0.2.dist-info/METADATA
odoo_addon_uom_unece-19.0.1.0.0.2.dist-info/WHEEL
odoo_addon_uom_unece-19.0.1.0.0.2.dist-info/top_level.txt
odoo_addon_uom_unece-19.0.1.0.0.2.dist-info/RECORD
