Metadata-Version: 2.1
Name: odoo-addon-uom_unece
Version: 19.0.1.0.0.2
Requires-Dist: odoo==19.0.*
Summary: UNECE nomenclature for the units of measure
Home-page: https://github.com/OCA/community-data-files
License: AGPL-3
Author: Akretion,Odoo Community Association (OCA)
Author-email: support@odoo-community.org
Classifier: Programming Language :: Python
Classifier: Framework :: Odoo
Classifier: Framework :: Odoo :: 19.0
Classifier: License :: OSI Approved :: GNU Affero General Public License v3
Classifier: Development Status :: 5 - Production/Stable
